antchain_sdk_dog_test/__init__.py
antchain_sdk_dog_test/client.py
antchain_sdk_dog_test/models.py
antchain_dog-1.1.23.dist-info/LICENSE
antchain_dog-1.1.23.dist-info/METADATA
antchain_dog-1.1.23.dist-info/WHEEL
antchain_dog-1.1.23.dist-info/top_level.txt
antchain_dog-1.1.23.dist-info/RECORD
